voraus_pipeline_utils/__init__.py
voraus_pipeline_utils/constants.py
voraus_pipeline_utils/py.typed
voraus_pipeline_utils/cli/__init__.py
voraus_pipeline_utils/cli/docker.py
voraus_pipeline_utils/cli/docs.py
voraus_pipeline_utils/cli/main.py
voraus_pipeline_utils/methods/__init__.py
voraus_pipeline_utils/methods/build.py
voraus_pipeline_utils/methods/docker.py
voraus_pipeline_utils/methods/docs.py
voraus_pipeline_utils/methods/environment.py
voraus_pipeline_utils/methods/shell.py
voraus_pipeline_utils-0.2.0.dist-info/licenses/LICENSE.txt
voraus_pipeline_utils-0.2.0.dist-info/METADATA
voraus_pipeline_utils-0.2.0.dist-info/WHEEL
voraus_pipeline_utils-0.2.0.dist-info/entry_points.txt
voraus_pipeline_utils-0.2.0.dist-info/top_level.txt
voraus_pipeline_utils-0.2.0.dist-info/RECORD
