Metadata-Version: 2.4
Name: voraus-pipeline-utils
Version: 0.2.0
Summary: A library containing pipeline utils for both, local usage and usage in Jenkins.
Author-email: Jan-Frederik Schmidt <jan-frederik.schmidt@vorausrobotik.com>
License: COMMERCIAL LICENSE (c) voraus robotik GmbH
Project-URL: Repository, https://github.com/vorausrobotik/voraus-pipeline-utils
Classifier: Programming Language :: Python
Classifier: Programming Language :: Python :: 3
Classifier: Programming Language :: Python :: 3 :: Only
Classifier: Programming Language :: Python :: 3.11
Classifier: Programming Language :: Python :: 3.12
Classifier: Programming Language :: Python :: 3.13
Classifier: Programming Language :: Python :: Implementation :: PyPy
Classifier: Typing :: Typed
Requires-Python: >=3.11
License-File: LICENSE.txt
Requires-Dist: importlib-metadata
Requires-Dist: typer
Requires-Dist: voraus-logging-lib
Requires-Dist: requests
Provides-Extra: dev
Requires-Dist: voraus-pipeline-utils[tox]; extra == "dev"
Requires-Dist: voraus-pipeline-utils[lint]; extra == "dev"
Requires-Dist: voraus-pipeline-utils[test]; extra == "dev"
Requires-Dist: voraus-pipeline-utils[doc]; extra == "dev"
Requires-Dist: voraus-pipeline-utils[build]; extra == "dev"
Provides-Extra: lint
Requires-Dist: voraus-pipeline-utils[lint-template]; extra == "lint"
Requires-Dist: types-requests; extra == "lint"
Provides-Extra: test
Requires-Dist: voraus-pipeline-utils[test-template]; extra == "test"
Provides-Extra: doc
Requires-Dist: voraus-pipeline-utils[doc-template]; extra == "doc"
Provides-Extra: build
Requires-Dist: voraus-pipeline-utils[build-template]; extra == "build"
Provides-Extra: tox
Requires-Dist: tox~=4.31.0; extra == "tox"
Requires-Dist: tox-uv~=1.29.0; extra == "tox"
Provides-Extra: lint-template
Requires-Dist: isort==6.0.0; extra == "lint-template"
Requires-Dist: black==25.1.0; extra == "lint-template"
Requires-Dist: mypy==1.15.0; extra == "lint-template"
Requires-Dist: pylint==3.3.4; extra == "lint-template"
Requires-Dist: pytest==8.3.4; extra == "lint-template"
Requires-Dist: doc8==1.1.2; extra == "lint-template"
Requires-Dist: types-docutils; extra == "lint-template"
Requires-Dist: types-setuptools; extra == "lint-template"
Requires-Dist: jinja2==3.1.5; extra == "lint-template"
Requires-Dist: ruff==0.9.5; extra == "lint-template"
Provides-Extra: test-template
Requires-Dist: pytest==8.3.4; extra == "test-template"
Requires-Dist: pytest-randomly==3.16.0; extra == "test-template"
Requires-Dist: pytest-cov==6.0.0; extra == "test-template"
Requires-Dist: coverage[toml]==7.6.11; extra == "test-template"
Provides-Extra: doc-template
Requires-Dist: sphinx==8.1.3; extra == "doc-template"
Requires-Dist: sphinxawesome-theme==5.3.2; extra == "doc-template"
Requires-Dist: sphinx-selective-exclude==1.0.3; extra == "doc-template"
Requires-Dist: sphinx-autodoc-typehints==3.0.1; extra == "doc-template"
Requires-Dist: pip-licenses==5.0.0; extra == "doc-template"
Requires-Dist: jinja2==3.1.5; extra == "doc-template"
Requires-Dist: snowballstemmer==2.2.0; extra == "doc-template"
Provides-Extra: build-template
Requires-Dist: build[virtualenv]==1.2.2.post1; extra == "build-template"
Dynamic: license-file
